manualindex/__init__.py
manualindex/__main__.py
manualindex/console.py
manualindex/manualindex.py
manualindex/py.typed
manualindex/templates/manualindex.html.j2
manualindex-1.0.1.dist-info/entry_points.txt
manualindex-1.0.1.dist-info/LICENSE.txt
manualindex-1.0.1.dist-info/WHEEL
manualindex-1.0.1.dist-info/METADATA
manualindex-1.0.1.dist-info/RECORD
