Metadata-Version: 2.1
Name: manualindex
Version: 1.0.1
Summary: Generate autoindex-style HTML for your directory listings.
Home-page: https://github.com/djmattyg007/manualindex
License: GPLv3
Keywords: autoindex,html,directory,listing
Author: Matthew Gamble
Author-email: git@matthewgamble.net
Requires-Python: >=3.9,<4.0
Classifier: Development Status :: 5 - Production/Stable
Classifier: Intended Audience :: Developers
Classifier: License :: OSI Approved :: GNU General Public License v3 (GPLv3)
Classifier: License :: Other/Proprietary License
Classifier: Operating System :: OS Independent
Classifier: Programming Language :: Python :: 3
Classifier: Programming Language :: Python :: 3.10
Classifier: Programming Language :: Python :: 3.9
Requires-Dist: Jinja2 (>=3.0.3,<4.0.0)
Requires-Dist: fs (>=2.4.14,<3.0.0)
Project-URL: Issues, https://github.com/djmattyg007/manualindex/issues
Project-URL: Repository, https://github.com/djmattyg007/manualindex
Project-URL: Source, https://github.com/djmattyg007/manualindex
